Metadata-Version: 2.1
Name: capibara-ent
Version: 1.2.1
Summary: A flexible multimodal AI library for advanced contextual understanding and deployment.
Home-page: https://github.com/anacronic-io/capibaraGPT-v2
Author: Marco Durán
Author-email: marco@anachroni.com
Keywords: ai nlp multimodal machine-learning deep-learning language-models ethics tpu training deployment
Classifier: Programming Language :: Python :: 3
Classifier: License :: OSI Approved :: MIT License
Classifier: Operating System :: OS Independent
Classifier: Development Status :: 4 - Beta
Classifier: Intended Audience :: Developers
Classifier: Intended Audience :: Science/Research
Classifier: Topic :: Scientific/Engineering :: Artificial Intelligence
Classifier: Topic :: Software Development :: Libraries :: Python Modules
Requires-Python: >=3.8
Requires-Dist: tensorflow>=2.5.0
Requires-Dist: docker
Requires-Dist: nltk
Requires-Dist: numpy
Requires-Dist: pandas
Requires-Dist: jax
Requires-Dist: flax
Requires-Dist: optax
Requires-Dist: wandb
Requires-Dist: tensorflow-hub
Requires-Dist: tqdm
Requires-Dist: PyYAML
Requires-Dist: spacy
Requires-Dist: transformers
Requires-Dist: scipy
Requires-Dist: matplotlib
Requires-Dist: seaborn
Provides-Extra: cloud_tpu
Requires-Dist: cloud-tpu-client; extra == "cloud-tpu"
Requires-Dist: google-auth; extra == "cloud-tpu"
Provides-Extra: dev
Requires-Dist: pytest; extra == "dev"
Requires-Dist: pytest-cov; extra == "dev"
Requires-Dist: sphinx; extra == "dev"
Requires-Dist: sphinx-rtd-theme; extra == "dev"
Requires-Dist: myst-parser; extra == "dev"
Requires-Dist: black; extra == "dev"
Requires-Dist: flake8; extra == "dev"
Provides-Extra: gpu
Requires-Dist: tensorflow-gpu>=2.5.0; extra == "gpu"
Provides-Extra: tpu
Requires-Dist: jax[tpu]>=0.2.21; extra == "tpu"
Requires-Dist: flax>=0.3.4; extra == "tpu"
Requires-Dist: optax>=0.0.9; extra == "tpu"
